docker_buddy/__init__.py
docker_buddy/_nbdev.py
docker_buddy/cli_colors.py
docker_buddy/docker_startup.py
docker_buddy-0.0.1.dist-info/LICENSE
docker_buddy-0.0.1.dist-info/METADATA
docker_buddy-0.0.1.dist-info/WHEEL
docker_buddy-0.0.1.dist-info/entry_points.txt
docker_buddy-0.0.1.dist-info/top_level.txt
docker_buddy-0.0.1.dist-info/RECORD
